{"['IL2DL']": 0, "['IL2VL']": 1, "['IL2L']": 2, "['URADL']": 3, "['IL1VL']": 4, "['IL2DR']": 5, "['IL1DL']": 6, "['OLLL']": 7, "['IL1L']": 8, "['URYDL']": 9, "['OLQDL']": 10, "['URYDR']": 11, "['IL2R']": 12, "['URYVL']": 13, "['RIPL']": 14, "['OLLR']": 15, "['URBL']": 16, "['IL2VR']": 17, "['IL1DR']": 18, "['URADR']": 19, "['IL1R']": 20, "['URAVL']": 21, "['OLQVL']": 22, "['RMED']": 23, "['URBR']": 24, "['OLQDR']": 25, "['URYVR']": 26, "['RIPR']": 27, "['RMEL']": 28, "['BAGL']": 29, "['CEPVL']": 30, "['BAGR']": 31, "['OLQVR']": 32, "['URAVR']": 33, "['RMER']": 34, "['IL1VR']": 35, "['RID']": 36, "['CEPVR']": 37, "['RMEV']": 38, "['CEPDL']": 39, "['RMDVL']": 40, "['SAAVL']": 41, "['SMDVL']": 42, "['URXL']": 43, "['ALA']": 44, "['RMDVR']": 45, "['CEPDR']": 46, "['AVAL']": 47, "['RIAL']": 48, "['ASKL']": 49, "['SAAVR']": 50, "['RMDL']": 51, "['URXR']": 52, "['SMDVR']": 53, "['AFDL']": 54, "['AVAR']": 55, "['RIAR']": 56, "['ASKR']": 57, "['AVEL']": 58, "['ADLL']": 59, "['ADFL']": 60, "['RMDR']": 61, "['AFDR']": 62, "['SIBDL']": 63, "['RIH']": 64, "['AWBL']": 65, "['AVER']": 66, "['RMDDL']": 67, "['AWCL']": 68, "['ADFR']": 69, "['ASGL']": 70, "['SAADL']": 71, "['ADLR']": 72, "['AWAL']": 73, "['AWBR']": 74, "['ASIL']": 75, "['ASHL']": 76, "['SIBDR']": 77, "['ASGR']": 78, "['AIBL']": 79, "['ASHR']": 80, "['AWCR']": 81, "['AWAR']": 82, "['SIBVL']": 83, "['RIVL']": 84, "['SMDDL']": 85, "['SAADR']": 86, "['RMHL']": 87, "['RMDDR']": 88, "['ASIR']": 89, "['AVHL']": 90, "['AVHR']": 91, "['RIVR']": 92, "['AIBR']": 93, "['RIBL']": 94, "['RMFL']": 95, "['AVBL']": 96, "['SIBVR']": 97, "['ASEL']": 98, "['AVJR']": 99, "['AUAL']": 100, "['SIADL']": 101, "['RMHR']": 102, "['AVJL']": 103, "['ASER']": 104, "['AVBR']": 105, "['RIBR']": 106, "['RMFR']": 107, "['SMDDR']": 108, "['AIAL']": 109, "['RIR']": 110, "['SMBDL']": 111, "['RIML']": 112, "['ASJL']": 113, "['RIMR']": 114, "['AUAR']": 115, "['AVDR']": 116, "['SMBVR']": 117, "['AVDL']": 118, "['AINL']": 119, "['SMBVL']": 120, "['ASJR']": 121, "['AINR']": 122, "['SIADR']": 123, "['AVL']": 124, "['RICL']": 125, "['AIAR']": 126, "['SMBDR']": 127, "['AIZR']": 128, "['SIAVL']": 129, "['SIAVR']": 130, "['RICR']": 131, "['AIZL']": 132, "['AIYR']": 133, "['AIMR']": 134, "['AIML']": 135, "['RIS']": 136, "['AIYL']": 137, "['VB02']": 138, "['AVKR']": 139, "['AVKL']": 140, "['AVFR']": 141, "['SABVL']": 142, "['FLPL']": 143, "['FLPR']": 144, "['SABVR']": 145, "['AVFL']": 146, "['AQR']": 147, "['RIFR']": 148, "['ADEL']": 149, "['VB01']": 150, "['ADER']": 151, "['DB02']": 152, "['ADAR']": 153, "['ADAL']": 154, "['RIGR']": 155, "['RMGL']": 156, "['RMGR']": 157, "['RIFL']": 158, "['AVG']": 159, "['VA01']": 160, "['SABD']": 161, "['RIGL']": 162, "['DD01']": 163, "['DB01']": 164, "['AS01']": 165, "['VD01']": 166, "['DA01']": 167, "['VD02']": 168, "['VA02']": 169, "['VB03']": 170, "['AS02']": 171, "['DB03']": 172, "['DA02']": 173, "['VD03']": 174, "['BDUR']": 175, "['BDUL']": 176, "['VA03']": 177, "['SDQR']": 178, "['VB04']": 179, "['VC01']": 180, "['DD02']": 181, "['AS03']": 182, "['VD04']": 183, "['DA03']": 184, "['VA04']": 185, "['VB05']": 186, "['VC02']": 187, "['DB04']": 188, "['AS04']": 189, "['VD05']": 190, "['VA05']": 191, "['AVM']": 192, "['VB06']": 193, "['DA04']": 194, "['DD03']": 195, "['ALML']": 196, "['ALMR']": 197, "['VC03']": 198, "['AS05']": 199, "['VD06']": 200, "['VA06']": 201, "['VB07']": 202, "['DB05']": 203, "['AS06']": 204, "['VD07']": 205, "['VC04']": 206, "['DA05']": 207, "['VC05']": 208, "['HSNR']": 209, "['HSNL']": 210, "['VA07']": 211, "['VB08']": 212, "['AS07']": 213, "['DD04']": 214, "['VD08']": 215, "['VA08']": 216, "['VB09']": 217, "['DB06']": 218, "['AS08']": 219, "['PDEL']": 220, "['VD09']": 221, "['PDER']": 222, "['SDQL']": 223, "['DA06']": 224, "['PVDL']": 225, "['PVDR']": 226, "['PVM']": 227, "['VA09']": 228, "['VB10']": 229, "['AS09']": 230, "['DD05']": 231, "['VD10']": 232, "['VA10']": 233, "['VB11']": 234, "['DB07']": 235, "['AS10']": 236, "['DA07']": 237, "['VD11']": 238, "['VA11']": 239, "['AS11']": 240, "['VD12']": 241, "['PVPR']": 242, "['PVT']": 243, "['VA12']": 244, "['DD06']": 245, "['PVPL']": 246, "['DA08']": 247, "['DA09']": 248, "['PDB']": 249, "['VD13']": 250, "['PDA']": 251, "['DVB']": 252, "['DVA']": 253, "['DVC']": 254, "['PVQR']": 255, "['PHAL']": 256, "['PHAR']": 257, "['PVQL']": 258, "['PLNR']": 259, "['LUAL']": 260, "['PVCL']": 261, "['PHBR']": 262, "['ALNL']": 263, "['PHBL']": 264, "['LUAR']": 265, "['ALNR']": 266, "['PVCR']": 267, "['PQR']": 268, "['PVR']": 269, "['PVWL']": 270, "['PVWR']": 271, "['PLNL']": 272, "['PHCR']": 273, "['PHCL']": 274, "['PVNR']": 275, "['PLMR']": 276, "['PVNL']": 277, "['PLML']": 278}